LICENSE
MANIFEST.in
README.md
pyproject.toml
requirements.txt
setup.cfg
setup.py
bgviewer/__init__.py
bgviewer.egg-info/PKG-INFO
bgviewer.egg-info/SOURCES.txt
bgviewer.egg-info/dependency_links.txt
bgviewer.egg-info/not-zip-safe
bgviewer.egg-info/requires.txt
bgviewer.egg-info/top_level.txt