Metadata-Version: 2.1
Name: bgviewer
Version: 0.0.1rc0
Summary: Visualisation and exploration of brain atlases
Home-page: https://github.com/brainglobe/bgviewer
Author: Adam Tyson, Luigi Petrucco, Federico Claudi
Author-email: adam.tyson@ucl.ac.uk
License: UNKNOWN
Platform: UNKNOWN
Classifier: Development Status :: 3 - Alpha
Classifier: Operating System :: POSIX :: Linux
Classifier: Operating System :: Microsoft :: Windows :: Windows 10
Classifier: Operating System :: MacOS :: MacOS X
Classifier: Programming Language :: Python
Classifier: Programming Language :: Python :: 3.6
Classifier: Programming Language :: Python :: 3.7
Classifier: Programming Language :: Python :: 3.8
Classifier: Intended Audience :: Developers
Classifier: Intended Audience :: Science/Research
Requires-Python: >=3.6, <3.8
Provides-Extra: dev
